pythere/__init__.py
pythere/__main__.py
pythere-0.2.dist-info/LICENSE
pythere-0.2.dist-info/METADATA
pythere-0.2.dist-info/WHEEL
pythere-0.2.dist-info/entry_points.txt
pythere-0.2.dist-info/top_level.txt
pythere-0.2.dist-info/RECORD
