Metadata-Version: 2.1
Name: pythere
Version: 0.2
Summary: pythere is a tool to run python scripts over ssh
Home-page: https://github.com/clint-lawrence/pythere
Author: Clint Lawrence
Author-email: clint.lawrence@gmail.com
License: LICENSE
Platform: UNKNOWN
Classifier: Development Status :: 4 - Beta
Classifier: Environment :: Console
Classifier: License :: OSI Approved :: MIT License
Classifier: Operating System :: OS Independent
Requires-Dist: fabric
